Metadata-Version: 2.1
Name: qeapp-xps
Version: 0.1.1
Summary: A plugin for calculating X-ray Photoelectron Spectroscopy (XPS) spectra.
Home-page: https://github.com/superstar54/qeapp-xps
Author: Xing Wang
Author-email: xingwang1991@gmail.com
Classifier: Development Status :: 3 - Alpha
Classifier: Intended Audience :: Developers
Classifier: License :: OSI Approved :: MIT License
Classifier: Programming Language :: Python :: 3
Classifier: Programming Language :: Python :: 3.9
Classifier: Programming Language :: Python :: 3.10
Classifier: Programming Language :: Python :: 3.11
Classifier: Programming Language :: Python :: 3.12
License-File: LICENSE
